gxdata/__init__.py
gxdata/jsoner.py
gxdata/texter.py
lib/gxdata/__init__.py
lib/gxdata/jsoner.py
lib/gxdata/texter.py
gxdata-0.1.dist-info/METADATA
gxdata-0.1.dist-info/WHEEL
gxdata-0.1.dist-info/top_level.txt
gxdata-0.1.dist-info/RECORD
