Metadata-Version: 2.1
Name: gxdata
Version: 0.1
Summary: data prepare toolkit
Home-page: UNKNOWN
Author: yat
Author-email: liangyi@bupt.edu.cn
License: MIT
Platform: UNKNOWN
Classifier: Programming Language :: Python :: 3.7
Classifier: License :: OSI Approved :: MIT License
Classifier: Operating System :: OS Independent
